setup.py
foobarxyz/__init__.py
foobarxyz.egg-info/PKG-INFO
foobarxyz.egg-info/SOURCES.txt
foobarxyz.egg-info/dependency_links.txt
foobarxyz.egg-info/not-zip-safe
foobarxyz.egg-info/top_level.txt