Metadata-Version: 1.0
Name: foobarxyz
Version: 0.1
Summary: Foo bar
Home-page: http://example.com/
Author: Changneng Chen
Author-email: changneng@example.com
License: MIT
Platform: UNKNOWN
